commonhandlers/__init__.py
commonhandlers/call_with_handlers_decorator.py
commonhandlers/handler.py
commonhandlers/handler_kind.py
commonhandlers/handlers.py
commonhandlers/iterate_with_handlers.py
commonhandlers-0.0.2.dist-info/METADATA
commonhandlers-0.0.2.dist-info/WHEEL
commonhandlers-0.0.2.dist-info/licenses/LICENSE
commonhandlers-0.0.2.dist-info/RECORD
