Metadata-Version: 2.3
Name: commonhandlers
Version: 0.0.2
Summary: Let you manage handlers, decorate function with handlers and iterate collections with handlers!
Project-URL: Github repo, https://github.com/akvilary/commonhandlers
Project-URL: Bug tracker, https://github.com/akvilary/commonhandlers/issues
Project-URL: Release notes in Telegram, https://t.me/commonhandlers
Author-email: Andrey Smirnov <smirnovcode@mail.ru>
License-File: LICENSE
Classifier: License :: CC0 1.0 Universal (CC0 1.0) Public Domain Dedication
Classifier: Operating System :: OS Independent
Classifier: Programming Language :: Python :: 3
Requires-Python: >=3.7
